LICENSE
MANIFEST.in
README.rst
setup.cfg
setup.py
aioquic/__init__.py
aioquic/buffer.py
aioquic/py.typed
aioquic/tls.py
aioquic/asyncio/__init__.py
aioquic/asyncio/client.py
aioquic/asyncio/compat.py
aioquic/asyncio/protocol.py
aioquic/asyncio/server.py
aioquic/h0/__init__.py
aioquic/h0/connection.py
aioquic/h3/__init__.py
aioquic/h3/connection.py
aioquic/h3/events.py
aioquic/h3/exceptions.py
aioquic/quic/__init__.py
aioquic/quic/configuration.py
aioquic/quic/connection.py
aioquic/quic/crypto.py
aioquic/quic/events.py
aioquic/quic/logger.py
aioquic/quic/packet.py
aioquic/quic/packet_builder.py
aioquic/quic/rangeset.py
aioquic/quic/recovery.py
aioquic/quic/retry.py
aioquic/quic/stream.py
aioquic_gcc49.egg-info/PKG-INFO
aioquic_gcc49.egg-info/SOURCES.txt
aioquic_gcc49.egg-info/dependency_links.txt
aioquic_gcc49.egg-info/requires.txt
aioquic_gcc49.egg-info/top_level.txt
docs/Makefile
docs/asyncio.rst
docs/conf.py
docs/design.rst
docs/h3.rst
docs/http_client.py
docs/index.rst
docs/license.rst
docs/quic.rst
examples/demo.py
examples/http3_client.py
examples/http3_server.py
examples/httpx_client.py
examples/interop.py
examples/templates/index.html
examples/templates/logs.html
src/_buffer.c
src/_crypto.c
tests/__init__.py
tests/initial_client.bin
tests/initial_server.bin
tests/pycacert.pem
tests/retry.bin
tests/short_header.bin
tests/ssl_cert.pem
tests/ssl_cert_with_chain.pem
tests/ssl_key.pem
tests/test_asyncio.py
tests/test_asyncio_compat.py
tests/test_buffer.py
tests/test_connection.py
tests/test_crypto.py
tests/test_h0.py
tests/test_h3.py
tests/test_logger.py
tests/test_packet.py
tests/test_packet_builder.py
tests/test_rangeset.py
tests/test_recovery.py
tests/test_retry.py
tests/test_stream.py
tests/test_tls.py
tests/tls_certificate.bin
tests/tls_certificate_verify.bin
tests/tls_client_hello.bin
tests/tls_client_hello_with_alpn.bin
tests/tls_client_hello_with_psk.bin
tests/tls_client_hello_with_sni.bin
tests/tls_encrypted_extensions.bin
tests/tls_encrypted_extensions_with_alpn.bin
tests/tls_encrypted_extensions_with_alpn_and_early_data.bin
tests/tls_finished.bin
tests/tls_new_session_ticket.bin
